stock_learning_rabbitmq_lib/ApiStub.py
stock_learning_rabbitmq_lib/QueueNameConstants.py
stock_learning_rabbitmq_lib/RabbitMQ.py
stock_learning_rabbitmq_lib/ScrapperStup.py
stock_learning_rabbitmq_lib/Stub.py
stock_learning_rabbitmq_lib/__init__.py
stock_learning_rabbitmq_lib-0.0.3.dist-info/LICENSE
stock_learning_rabbitmq_lib-0.0.3.dist-info/METADATA
stock_learning_rabbitmq_lib-0.0.3.dist-info/WHEEL
stock_learning_rabbitmq_lib-0.0.3.dist-info/top_level.txt
stock_learning_rabbitmq_lib-0.0.3.dist-info/RECORD
