Metadata-Version: 2.1
Name: stock-learning-rabbitmq-lib
Version: 0.0.3
Summary: This is a package that includes all RabbitMQ handled messages by the stock-learning infrastructure
Home-page: https://github.com/vinicius-lds/stock-learning-rabbitmq-lib
Author: Vinícius Luis da Silva
Author-email: vinicius.lds.br@gmail.com
License: UNKNOWN
Platform: UNKNOWN
Classifier: Programming Language :: Python :: 3
Classifier: License :: OSI Approved :: MIT License
Classifier: Operating System :: OS Independent
Requires-Python: >=3.6
